{"Disney":{"matches":["disney","disneyland","mickey mouse"],"gender":"Both"},"Airplanes":{"matches":["airplane"],"gender":"Male"},"Trucks":{"matches":["trucker","truck"],"gender":"Male"},"Animals":{"matches":["animal","dog","cat","puppy","doggie","dolphin","giraffe","goose","hamster","kangaroo","lion","horse","goat","shark","squirrel","bunny","duckling","rabbit","raccoon","panda","whale","penguin","pig","snake","mouse","beaver","bird","bull","camel","chameleon","cobra","cow","coyote","crocodile","dinosaur","duck","elephant","eagle","flamingo","fox","gorilla","hedgehog","hippopotamus","hyena","koala","ladybug","leopard","lizard","moose","mosquito","ostrich","owl","parrot","pigeon","bear","seagull","seal","sheep","tiger","turtle","woodpecker","zebra","frog","bee","rooster","monkey","donkey","butterfly","alligator","alpaca","antelope","ape","armadilo","badget","buffalo","bison","boar","cattke","cheetah","cockroach","crow","deer","elk","emi","falcon","ferret","grasshopper","grouse","gnat","hummingbird","raccoonreindeer","skunk","sparrow","rat","pronghorn","quail","platypus","oyster","otter","porpoise","rhinoceros","toad","trout","wasp","weasel","caterpillar","ducklinginsect","ant","wolf","calf","spider","pet"],"gender":"Both"},"Basketball":{"matches":["Basketball"],"gender":"Both"},"Football":{"matches":["Football"],"gender":"Both"},"Soccer":{"matches":["Soccer"],"gender":"Both"},"Flowers":{"matches":["Flowers"],"gender":"Female"},"Kings":{"matches":["king"],"gender":"Male"},"Princesses":{"matches":["Princess"],"gender":"Female"},"Firemen":{"matches":["Firemen","Fireman"],"gender":"Male"},"Policemen":{"matches":["Policeman","police man","policemen","police men"],"gender":"Male"},"Cars":{"matches":["car"],"gender":"Male"},"Fashion":{"matches":["fashion"],"gender":"Female"},"Makeup":{"matches":["makeup"],"gender":"Female"},"Accessories ":{"matches":["Accessories","accessory"],"gender":"Female"},"Fairy Tales":{"matches":["fairytale","fair tale"],"gender":"Both"},"Colouring":{"matches":["colouring","coloring","painting","drawing","crayons","pencil","brush"],"gender":"Both"},"Dinosaurs":{"matches":["dinosaurs"],"gender":"Both"},"Music":{"matches":["musical instruments","guitar","piano","flute","drum","trumpet","clarinet","violin","musical note","music note","musical soundtrack","background music","accordion","xylophone","saxhorn","harp","instrument"],"gender":"Both"},"Sports":{"matches":["sports","basketball","football","baseball","soccer","hockey","ballet","martial arts","karate","taekwondo","running","golf","handball","archery","badminton","boxing","cricket","fencing","gymnastics","horse racing","rugby","softball","table tennis","tennis","volleyball"],"gender":"Both"},"Trains":{"matches":["train"],"gender":"Male"},"Zoo":{"matches":[],"gender":"Both"},"Aquariums":{"matches":["aquarium"],"gender":"Both"},"Astronauts":{"matches":["astronaut"],"gender":"Both"},"Bicycles":{"matches":["bicycle"],"gender":"Both"},"Kites":{"matches":["kites"],"gender":"Both"},"Arts and craft":{"matches":["arts and craft","art and craft","art","craft","origami"],"gender":"Both"},"Balloons":{"matches":["balloon"],"gender":"Both"},"Bubbles":{"matches":["bubble"],"gender":"Both"},"Soldiers":{"matches":["Soldier"],"gender":"Male"},"Stars":{"matches":["stars"],"gender":"Both"},"Barbies":{"matches":["barbie"],"gender":"Both"},"No in-app purchases":{"matches":["does not contain in-app purchases","doesn't contain in-app purchase","no in-app purchase","doesn't have in-app purchase","does not have in-app purchase"],"gender":"Both"},"Flags":{"matches":["flags"],"gender":"Both"},"Maps":{"matches":["map"],"gender":"Both"},"Audio":{"matches":["sound recognition","recognize sound","voice recognition","recognize voice","voiceover","soundover","record narrative in your voice","auditory processing","audio clips","sounds object make","listening","background sounds","voice record","tap and listen","see and hear"],"gender":"Both"},"Water Sports":{"matches":["sailing","canoe","swimming","scuba diving","scuba-diving","surfing","kayak","canoeing","kayaking","boat race","boat racing","rowing"],"gender":"Both"},"Pirate":{"matches":["pirate"],"gender":"Both"},"Captains":{"matches":["captain"],"gender":"Both"},"Duration":{"matches":["long car ride","waiting in line","while cooking your meal","on a plane","at a restaurant"],"gender":"Both"},"Compass":{"matches":["direction compass","compass"],"gender":"Both"},"Magic":{"matches":["magic","magical"],"gender":"Both"},"Days of the week":{"matches":["days of the week"],"gender":"Both"},"Seasons":{"matches":["4 seasons","four seasons"],"gender":"Both"},"Puzzles":{"matches":["puzzles"],"gender":"Both"},"Video":{"matches":["video","animated movie"],"gender":"Both"},"Camera":{"matches":["camera"],"gender":"Both"},"Photography":{"matches":["Photography"],"gender":"Both"},"Bus":{"matches":["bus"],"gender":"Both"},"Helicopter":{"matches":["Helicopter"],"gender":"Both"},"Motorcycle":{"matches":["Motorcycle"],"gender":"Both"},"Bicycle":{"matches":["Bicycle"],"gender":"Both"},"Songs":{"matches":["song","singing","sing","sing along","children songs","rhyme","nursery rhyme","lyrics","lallabies","lullaby","lullabies","musical soundtrack","verse"],"gender":"Both"},"Food & Beverage":{"matches":[],"gender":"Both"},"Decoration":{"matches":["decorate","decorations"],"gender":"Both"},"Fantasy":{"matches":["Fantasy"],"gender":"Both"},"Horsecope":{"matches":["Horsecope"],"gender":"Both"},"Quiz":{"matches":["quiz"],"gender":"Both"},"Humorous":{"matches":["humour","humor","humorous"],"gender":"Both"},"TED talks":{"matches":["TED talks","TED conference","TEDtalk"],"gender":"Both"},"Ambulance":{"matches":["Ambulance"],"gender":"Both"},"Police car":{"matches":["police car"],"gender":"Both"},"Cartoon":{"matches":["cartoon"],"gender":"Both"},"Special Occasions":{"matches":["special holidays","halloween","new year","christmas","thanksgiving","birthday"],"gender":"Both"},"Alice in the Wonderland":{"matches":["Alice in the Wonderland"],"gender":"Female"},"Boy Scouts":{"matches":["Boy Scouts"],"gender":"Male"},"Clifford":{"matches":["Clifford"],"gender":"Both"},"Club Penguin":{"matches":["Club Penguin"],"gender":"Both"},"Curious George":{"matches":["Curious George"],"gender":"Both"},"Dora the Explorer ":{"matches":["Dora the Explorer"],"gender":"Female"},"Dr. Seuss":{"matches":["Dr. Seuss"],"gender":"Both"},"Elmo":{"matches":["Elmo"],"gender":"Both"},"Etch a Sketch":{"matches":["Etch a Sketch"],"gender":"Both"},"Garfield":{"matches":["Garfield"],"gender":"Both"},"Hans Christian Andersen":{"matches":["Hans Christian Andersen"],"gender":"Both"},"Jack and the Beanstalk":{"matches":["Jack and the Beanstalk"],"gender":"Both"},"Lego":{"matches":["Lego"],"gender":"Both"},"Lite Brite":{"matches":["Lite Brite"],"gender":"Both"},"Little Red Riding Hood":{"matches":["Little Red Riding Hood"],"gender":"Female"},"NASA":{"matches":["NASA"],"gender":"Both"},"National Geographic":{"matches":["National Geographic"],"gender":"Both"},"Nickelodeon":{"matches":["Nickelodeon"],"gender":"Both"},"PBS Kids":{"matches":["PBS Kids"],"gender":"Both"},"Pixar":{"matches":["Pixar"],"gender":"Both"},"Scholastic":{"matches":["Scholastic"],"gender":"Both"},"Sesame Street":{"matches":["Sesame Street"],"gender":"Both"},"Shrek":{"matches":["Shrek"],"gender":"Both"},"Star Wars":{"matches":["Star Wars"],"gender":"Both"},"Thomas the Tank Engine":{"matches":["Thomas the Tank Engine"],"gender":"Both"},"Three Little Pigs":{"matches":["Three Little Pigs"],"gender":"Both"},"Wallace & Gromit":{"matches":["Wallace & Gromit"],"gender":"Both"},"Where's Waldo?":{"matches":["Where's Waldo?"],"gender":"Both"},"Cooking":{"matches":["cooking","cook","ingredient","fry","boil","slice"],"gender":"Both"},"Kitchen":{"matches":["kitchen"],"gender":"Both"},"Playground":{"matches":["Playground"],"gender":"Both"},"Memory game":{"matches":["memory game","memory card matching","memory match","matching card","matching game","memory aid","visual memory"],"gender":"Both"},"Safari":{"matches":["Safari"],"gender":"Both"},"Farm":{"matches":["farm"],"gender":"Both"},"Water animal":{"matches":["Water animal","sea animal","underwater animal","ocean animal","aquarium","fish","codfish","eel","shark","seal","whale","jellyfish","toad"],"gender":"Both"},"Old Macdonald Had a Farm":{"matches":["Old Macdonald Had a Farm"],"gender":"Both"},"TV":{"matches":["tv series","televesion series","station tv"],"gender":"Both"},"Connect the dots":{"matches":["Connect the dots"],"gender":"Both"},"Sorting":{"matches":["sorting"],"gender":"Both"},"Pattern":{"matches":["find the Pattern","Pattern recognition"],"gender":"Both"},"Sequences":{"matches":["sequence","number sequence","sequencing"],"gender":"Both"}}